aiogetui/__init__.py
aiogetui/client.py
aiogetui/common.py
aiogetui/exceptions.py
aiogetui/template.py
aiogetui-0.4.dist-info/LICENSE
aiogetui-0.4.dist-info/METADATA
aiogetui-0.4.dist-info/WHEEL
aiogetui-0.4.dist-info/top_level.txt
aiogetui-0.4.dist-info/RECORD
