Metadata-Version: 2.1
Name: aiogetui
Version: 0.4
Summary: Python SDK for Getui push service based on asyncio(aiohttp).
Home-page: https://github.com/charact3/aiogetui
Author: Darren Char
Author-email: i@charact3.com
License: MIT
Platform: UNKNOWN
Classifier: License :: OSI Approved :: MIT License
Classifier: Programming Language :: Python
Classifier: Programming Language :: Python :: 3
Classifier: Programming Language :: Python :: 3.6
Classifier: Programming Language :: Python :: Implementation :: CPython
Classifier: Programming Language :: Python :: Implementation :: PyPy
Requires-Python: >=3.6.0
Requires-Dist: six
Requires-Dist: aiohttp (<4.0,>3.0)
